{
  "type": "minecraft:crafting_shaped",
  "category": "misc",
  "key": {
    "I": {
      "tag": "c:ingots/steel"
    },
    "W": {
      "type": "neoforge:components",
      "components": {
        "minecraft:custom_data": {
          "material": "red_copper"
        },
        "minecraft:custom_model_data": 31
      },
      "items": "hbm:wire_fine",
      "strict": true
    }
  },
  "pattern": [
    "WWW",
    "WIW",
    "WWW"
  ],
  "result": {
    "count": 1,
    "id": "hbm:coil_copper"
  }
}